[
    {
        "timestamp": "2025-11-28T22:01:19.503543+00:00",
        "value": "==ignored-doctors-flat-solve==",
        "change": "initial"
    },
    {
        "timestamp": "2025-11-28T22:16:23.125062+00:00",
        "value": "==jump-reviewing-tan-mhz==",
        "change": "update"
    },
    {
        "timestamp": "2025-11-28T23:16:37.613428+00:00",
        "value": "==scenic-briefs-wilderness-arbitration==",
        "change": "update"
    },
    {
        "timestamp": "2025-11-29T00:16:51.901674+00:00",
        "value": "==pdf-pair-mixing-outstanding==",
        "change": "update"
    },
    {
        "timestamp": "2025-11-29T01:17:05.989824+00:00",
        "value": "==celtic-hang-able-rpm==",
        "change": "update"
    },
    {
        "timestamp": "2025-11-29T02:17:20.234514+00:00",
        "value": "==script-church-clothing-bradley==",
        "change": "update"
    },
    {
        "timestamp": "2025-11-29T03:17:34.272148+00:00",
        "value": "==antarctica-introducing-milan-francisco==",
        "change": "update"
    }
]